[
  {
    "orderId": 462,
    "orderNumber": "026-1919428-2815565",
    "items": [
      {
        "itemId": 491,
        "productName": "1-Colour Keyring (Prime)",
        "customText": null,
        "color1": null,
        "color2": null
      },
      {
        "itemId": 492,
        "productName": "1-Colour Keyring (Prime)",
        "customText": null,
        "color1": null,
        "color2": null
      },
      {
        "itemId": 493,
        "productName": "1-Colour Keyring (Prime)",
        "customText": null,
        "color1": null,
        "color2": null
      }
    ]
  },
  {
    "orderId": 461,
    "orderNumber": "202-9124397-4634701",
    "items": [
      {
        "itemId": 490,
        "productName": "1-Colour Keyring (Prime)",
        "customText": null,
        "color1": null,
        "color2": null
      }
    ]
  },
  {
    "orderId": 460,
    "orderNumber": "204-6585836-4459555",
    "items": [
      {
        "itemId": 489,
        "productName": "Personalised Keyring - Custom 3D Name Tag with 24 Colours for Kids' Bags & Party Favours | Unique Personalised Gifts for Kids | 2-Colour Design Keychain for School Bags & Stocking Fillers",
        "customText": null,
        "color1": null,
        "color2": null
      }
    ]
  },
  {
    "orderId": 455,
    "orderNumber": "204-7539439-5889959",
    "items": [
      {
        "itemId": 483,
        "productName": "2-Colour Keyring",
        "customText": null,
        "color1": null,
        "color2": null
      },
      {
        "itemId": 484,
        "productName": "2-Colour Keyring",
        "customText": null,
        "color1": null,
        "color2": null
      }
    ]
  },
  {
    "orderId": 456,
    "orderNumber": "205-5498098-6266763",
    "items": [
      {
        "itemId": 485,
        "productName": "1-Colour Keyring",
        "customText": null,
        "color1": null,
        "color2": null
      }
    ]
  },
  {
    "orderId": 453,
    "orderNumber": "206-5736461-1732357",
    "items": [
      {
        "itemId": 481,
        "productName": "Building Block Style Letter Keyring, Personalised Initial A-Z, Party Favour, Colourful Alphabet Gift",
        "customText": null,
        "color1": null,
        "color2": null
      }
    ]
  },
  {
    "orderId": 386,
    "orderNumber": "204-3491751-7669153",
    "items": [
      {
        "itemId": 389,
        "productName": "1-Colour Keyring (Prime)",
        "customText": null,
        "color1": null,
        "color2": null
      }
    ]
  },
  {
    "orderId": 377,
    "orderNumber": "026-3738072-6631538",
    "items": [
      {
        "itemId": 373,
        "productName": "1-Colour Keyring",
        "customText": null,
        "color1": null,
        "color2": null
      },
      {
        "itemId": 374,
        "productName": "1-Colour Keyring",
        "customText": null,
        "color1": null,
        "color2": null
      }
    ]
  },
  {
    "orderId": 375,
    "orderNumber": "202-3650165-4526726",
    "items": [
      {
        "itemId": 369,
        "productName": "1-Colour Keyring",
        "customText": null,
        "color1": null,
        "color2": null
      },
      {
        "itemId": 370,
        "productName": "1-Colour Keyring",
        "customText": null,
        "color1": null,
        "color2": null
      },
      {
        "itemId": 371,
        "productName": "1-Colour Keyring",
        "customText": null,
        "color1": null,
        "color2": null
      }
    ]
  },
  {
    "orderId": 371,
    "orderNumber": "203-0396633-6943563",
    "items": [
      {
        "itemId": 363,
        "productName": "1-Colour Keyring",
        "customText": null,
        "color1": null,
        "color2": null
      },
      {
        "itemId": 364,
        "productName": "1-Colour Keyring",
        "customText": null,
        "color1": null,
        "color2": null
      }
    ]
  },
  {
    "orderId": 198,
    "orderNumber": "206-6951810-4949116",
    "items": [
      {
        "itemId": 315,
        "productName": "1-Colour Keyring",
        "customText": null,
        "color1": null,
        "color2": null
      }
    ]
  },
  {
    "orderId": 201,
    "orderNumber": "202-7234738-1641948",
    "items": [
      {
        "itemId": 318,
        "productName": "1-Colour Keyring",
        "customText": null,
        "color1": null,
        "color2": null
      }
    ]
  },
  {
    "orderId": 207,
    "orderNumber": "202-1111760-0782736",
    "items": [
      {
        "itemId": 328,
        "productName": "1-Colour Keyring",
        "customText": null,
        "color1": null,
        "color2": null
      },
      {
        "itemId": 329,
        "productName": "1-Colour Keyring",
        "customText": null,
        "color1": null,
        "color2": null
      }
    ]
  },
  {
    "orderId": 125,
    "orderNumber": "206-4613066-3349968",
    "items": [
      {
        "itemId": 200,
        "productName": "1-Colour Keyring",
        "customText": null,
        "color1": null,
        "color2": null
      },
      {
        "itemId": 201,
        "productName": "1-Colour Keyring",
        "customText": null,
        "color1": null,
        "color2": null
      },
      {
        "itemId": 202,
        "productName": "1-Colour Keyring",
        "customText": null,
        "color1": null,
        "color2": null
      }
    ]
  },
  {
    "orderId": 115,
    "orderNumber": "204-3691016-4480362",
    "items": [
      {
        "itemId": 184,
        "productName": "1-Colour Keyring",
        "customText": null,
        "color1": null,
        "color2": null
      },
      {
        "itemId": 185,
        "productName": "1-Colour Keyring",
        "customText": null,
        "color1": null,
        "color2": null
      },
      {
        "itemId": 186,
        "productName": "1-Colour Keyring",
        "customText": null,
        "color1": null,
        "color2": null
      }
    ]
  },
  {
    "orderId": 117,
    "orderNumber": "206-5862293-3742702",
    "items": [
      {
        "itemId": 189,
        "productName": "1-Colour Keyring",
        "customText": null,
        "color1": null,
        "color2": null
      }
    ]
  },
  {
    "orderId": 112,
    "orderNumber": "204-1724500-8572335",
    "items": [
      {
        "itemId": 180,
        "productName": "1-Colour Keyring",
        "customText": null,
        "color1": null,
        "color2": null
      }
    ]
  },
  {
    "orderId": 104,
    "orderNumber": "204-2833980-7732328",
    "items": [
      {
        "itemId": 162,
        "productName": "1-Colour Keyring",
        "customText": null,
        "color1": null,
        "color2": null
      }
    ]
  },
  {
    "orderId": 105,
    "orderNumber": "204-6695906-3617136",
    "items": [
      {
        "itemId": 163,
        "productName": "1-Colour Keyring (Prime)",
        "customText": null,
        "color1": null,
        "color2": null
      },
      {
        "itemId": 164,
        "productName": "1-Colour Keyring (Prime)",
        "customText": null,
        "color1": null,
        "color2": null
      },
      {
        "itemId": 165,
        "productName": "1-Colour Keyring (Prime)",
        "customText": null,
        "color1": null,
        "color2": null
      }
    ]
  },
  {
    "orderId": 98,
    "orderNumber": "203-0826267-2037149",
    "items": [
      {
        "itemId": 156,
        "productName": "1-Colour Keyring",
        "customText": null,
        "color1": null,
        "color2": null
      }
    ]
  },
  {
    "orderId": 99,
    "orderNumber": "205-6569546-4051535",
    "items": [
      {
        "itemId": 157,
        "productName": "1-Colour Keyring",
        "customText": null,
        "color1": null,
        "color2": null
      }
    ]
  },
  {
    "orderId": 14,
    "orderNumber": "205-8758185-4942713",
    "items": [
      {
        "itemId": 23,
        "productName": "1-Colour Keyring",
        "customText": null,
        "color1": null,
        "color2": null
      },
      {
        "itemId": 24,
        "productName": "1-Colour Keyring",
        "customText": null,
        "color1": null,
        "color2": null
      }
    ]
  },
  {
    "orderId": 615,
    "orderNumber": "203-4543683-6449169",
    "items": [
      {
        "itemId": 799,
        "productName": "2-Colour Keyring",
        "customText": null,
        "color1": null,
        "color2": null
      }
    ]
  },
  {
    "orderId": 616,
    "orderNumber": "026-5585200-4785105",
    "items": [
      {
        "itemId": 816,
        "productName": "2-Colour Keyring",
        "customText": null,
        "color1": null,
        "color2": null
      },
      {
        "itemId": 817,
        "productName": "2-Colour Keyring",
        "customText": null,
        "color1": null,
        "color2": null
      },
      {
        "itemId": 818,
        "productName": "2-Colour Keyring",
        "customText": null,
        "color1": null,
        "color2": null
      },
      {
        "itemId": 819,
        "productName": "2-Colour Keyring",
        "customText": null,
        "color1": null,
        "color2": null
      },
      {
        "itemId": 820,
        "productName": "2-Colour Keyring",
        "customText": null,
        "color1": null,
        "color2": null
      },
      {
        "itemId": 821,
        "productName": "2-Colour Keyring",
        "customText": null,
        "color1": null,
        "color2": null
      },
      {
        "itemId": 822,
        "productName": "2-Colour Keyring",
        "customText": null,
        "color1": null,
        "color2": null
      },
      {
        "itemId": 823,
        "productName": "2-Colour Keyring",
        "customText": null,
        "color1": null,
        "color2": null
      }
    ]
  },
  {
    "orderId": 617,
    "orderNumber": "204-0816355-6207508",
    "items": [
      {
        "itemId": 824,
        "productName": "2-Colour Keyring",
        "customText": null,
        "color1": null,
        "color2": null
      }
    ]
  },
  {
    "orderId": 622,
    "orderNumber": "205-7366202-0271560",
    "items": [
      {
        "itemId": 837,
        "productName": "1-Colour Keyring",
        "customText": null,
        "color1": null,
        "color2": null
      },
      {
        "itemId": 838,
        "productName": "1-Colour Keyring",
        "customText": null,
        "color1": null,
        "color2": null
      }
    ]
  },
  {
    "orderId": 623,
    "orderNumber": "203-2673583-5481130",
    "items": [
      {
        "itemId": 839,
        "productName": "1-Colour Keyring",
        "customText": null,
        "color1": null,
        "color2": null
      },
      {
        "itemId": 840,
        "productName": "1-Colour Keyring",
        "customText": null,
        "color1": null,
        "color2": null
      },
      {
        "itemId": 841,
        "productName": "1-Colour Keyring",
        "customText": null,
        "color1": null,
        "color2": null
      }
    ]
  },
  {
    "orderId": 624,
    "orderNumber": "202-2458726-5256332",
    "items": [
      {
        "itemId": 842,
        "productName": "2-Colour Keyring",
        "customText": null,
        "color1": null,
        "color2": null
      }
    ]
  },
  {
    "orderId": 625,
    "orderNumber": "026-8045936-0600319",
    "items": [
      {
        "itemId": 843,
        "productName": "1-Colour Keyring",
        "customText": null,
        "color1": null,
        "color2": null
      }
    ]
  },
  {
    "orderId": 629,
    "orderNumber": "204-5678075-4093927",
    "items": [
      {
        "itemId": 853,
        "productName": "Personalised Game Controller Keyring/Keychain for Party Bag Filling",
        "customText": null,
        "color1": null,
        "color2": null
      }
    ]
  },
  {
    "orderId": 632,
    "orderNumber": "206-0965578-3685925",
    "items": [
      {
        "itemId": 867,
        "productName": "2-Colour Keyring",
        "customText": null,
        "color1": null,
        "color2": null
      },
      {
        "itemId": 868,
        "productName": "2-Colour Keyring",
        "customText": null,
        "color1": null,
        "color2": null
      },
      {
        "itemId": 869,
        "productName": "2-Colour Keyring",
        "customText": null,
        "color1": null,
        "color2": null
      },
      {
        "itemId": 870,
        "productName": "2-Colour Keyring",
        "customText": null,
        "color1": null,
        "color2": null
      }
    ]
  },
  {
    "orderId": 631,
    "orderNumber": "202-7013581-4597156",
    "items": [
      {
        "itemId": 864,
        "productName": "1-Colour Keyring (Prime)",
        "customText": null,
        "color1": null,
        "color2": null
      },
      {
        "itemId": 865,
        "productName": "1-Colour Keyring (Prime)",
        "customText": null,
        "color1": null,
        "color2": null
      },
      {
        "itemId": 866,
        "productName": "1-Colour Keyring (Prime)",
        "customText": null,
        "color1": null,
        "color2": null
      }
    ]
  }
]